rudra/__init__.py
rudra/admin.py
rudra/apps.py
rudra/models.py
rudra/paginator.py
rudra/service.py
rudra/settings.py
rudra/tests.py
rudra/urls.py
rudra/views.py
django_rudra-0.1.7.dist-info/LICENSE
django_rudra-0.1.7.dist-info/METADATA
django_rudra-0.1.7.dist-info/WHEEL
django_rudra-0.1.7.dist-info/top_level.txt
django_rudra-0.1.7.dist-info/RECORD
